stacktyping.py
stacktyping-1.2.0.dist-info/LICENSE
stacktyping-1.2.0.dist-info/METADATA
stacktyping-1.2.0.dist-info/WHEEL
stacktyping-1.2.0.dist-info/top_level.txt
stacktyping-1.2.0.dist-info/RECORD
