Metadata-Version: 2.1
Name: stacktyping
Version: 1.2.0
Summary: Py Stack developed based on C++
Author: ChewangNeko
Author-email: 2745283841@qq.com
Classifier: Programming Language :: Python :: 3
Classifier: License :: OSI Approved :: MIT License
Classifier: Operating System :: OS Independent
License-File: LICENSE
